amino/__init__.py
amino/acm.py
amino/client.py
amino/d.py
amino/socket.py
amino/sub_client.py
amino/lib/__init__.py
amino/lib/util/__init__.py
amino/lib/util/d.py
amino/lib/util/device.py
amino/lib/util/exceptions.py
amino/lib/util/headers.py
amino/lib/util/helpers.py
amino/lib/util/objects.py
amino/lib/util/voice_header.py
new/__init__.py
new/acm.py
new/client.py
new/socket.py
new/sub_client.py
new/lib/__init__.py
new/lib/util/__init__.py
new/lib/util/device.py
new/lib/util/exceptions.py
new/lib/util/headers.py
new/lib/util/helpers.py
new/lib/util/objects.py
new/lib/util/voice_header.py
Amino_new.py-5.0.dist-info/METADATA
Amino_new.py-5.0.dist-info/WHEEL
Amino_new.py-5.0.dist-info/top_level.txt
Amino_new.py-5.0.dist-info/RECORD
